{"nodes": [{"id": "src_unified_algebra_validation_py", "label": "validation.py", "file_type": "code", "source_file": "src/unified_algebra/validation.py", "source_location": "L1"}, {"id": "validation_eq_name", "label": "_eq_name()", "file_type": "code", "source_file": "src/unified_algebra/validation.py", "source_location": "L26"}, {"id": "validation_eq_inputs", "label": "_eq_inputs()", "file_type": "code", "source_file": "src/unified_algebra/validation.py", "source_location": "L30"}, {"id": "validation_any_has_inputs", "label": "_any_has_inputs()", "file_type": "code", "source_file": "src/unified_algebra/validation.py", "source_location": "L35"}, {"id": "validation_resolve_dag", "label": "resolve_dag()", "file_type": "code", "source_file": "src/unified_algebra/validation.py", "source_location": "L43"}, {"id": "validation_validate_dag", "label": "_validate_dag()", "file_type": "code", "source_file": "src/unified_algebra/validation.py", "source_location": "L83"}, {"id": "validation_validate_pipeline", "label": "validate_pipeline()", "file_type": "code", "source_file": "src/unified_algebra/validation.py", "source_location": "L90"}, {"id": "validation_ua_primitives", "label": "ua_primitives()", "file_type": "code", "source_file": "src/unified_algebra/validation.py", "source_location": "L107"}, {"id": "validation_rationale_1", "label": "DAG validation and pipeline checking for equation sets.  Handles topological ord", "file_type": "rationale", "source_file": "src/unified_algebra/validation.py", "source_location": "L1"}, {"id": "validation_rationale_44", "label": "Return all (upstream, downstream, input_slot) edges in topological order.      R", "file_type": "rationale", "source_file": "src/unified_algebra/validation.py", "source_location": "L44"}, {"id": "validation_rationale_91", "label": "Check sort and rank junctions across equations.      Linear mode: when no equati", "file_type": "rationale", "source_file": "src/unified_algebra/validation.py", "source_location": "L91"}, {"id": "validation_rationale_111", "label": "Resolve all equation terms into Hydra Primitives.      Follows the same pattern", "file_type": "rationale", "source_file": "src/unified_algebra/validation.py", "source_location": "L111"}], "edges": [{"source": "src_unified_algebra_validation_py", "target": "collections", "relation": "imports_from", "confidence": "EXTRACTED", "source_file": "src/unified_algebra/validation.py", "source_location": "L9", "weight": 1.0}, {"source": "src_unified_algebra_validation_py", "target": "typing", "relation": "imports_from", "confidence": "EXTRACTED", "source_file": "src/unified_algebra/validation.py", "source_location": "L10", "weight": 1.0}, {"source": "src_unified_algebra_validation_py", "target": "unified_algebra_utils", "relation": "imports_from", "confidence": "EXTRACTED", "source_file": "src/unified_algebra/validation.py", "source_location": "L12", "weight": 1.0}, {"source": "src_unified_algebra_validation_py", "target": "src_unified_algebra_sort_py", "relation": "imports_from", "confidence": "EXTRACTED", "source_file": "src/unified_algebra/validation.py", "source_location": "L13", "weight": 1.0}, {"source": "src_unified_algebra_validation_py", "target": "src_unified_algebra_morphism_py", "relation": "imports_from", "confidence": "EXTRACTED", "source_file": "src/unified_algebra/validation.py", "source_location": "L14", "weight": 1.0}, {"source": "src_unified_algebra_validation_py", "target": "hydra_core", "relation": "imports", "confidence": "EXTRACTED", "source_file": "src/unified_algebra/validation.py", "source_location": "L17", "weight": 1.0}, {"source": "src_unified_algebra_validation_py", "target": "hydra_graph", "relation": "imports", "confidence": "EXTRACTED", "source_file": "src/unified_algebra/validation.py", "source_location": "L18", "weight": 1.0}, {"source": "src_unified_algebra_validation_py", "target": "src_unified_algebra_backend_py", "relation": "imports_from", "confidence": "EXTRACTED", "source_file": "src/unified_algebra/validation.py", "source_location": "L19", "weight": 1.0}, {"source": "src_unified_algebra_validation_py", "target": "validation_eq_name", "relation": "contains", "confidence": "EXTRACTED", "source_file": "src/unified_algebra/validation.py", "source_location": "L26", "weight": 1.0}, {"source": "src_unified_algebra_validation_py", "target": "validation_eq_inputs", "relation": "contains", "confidence": "EXTRACTED", "source_file": "src/unified_algebra/validation.py", "source_location": "L30", "weight": 1.0}, {"source": "src_unified_algebra_validation_py", "target": "validation_any_has_inputs", "relation": "contains", "confidence": "EXTRACTED", "source_file": "src/unified_algebra/validation.py", "source_location": "L35", "weight": 1.0}, {"source": "src_unified_algebra_validation_py", "target": "validation_resolve_dag", "relation": "contains", "confidence": "EXTRACTED", "source_file": "src/unified_algebra/validation.py", "source_location": "L43", "weight": 1.0}, {"source": "src_unified_algebra_validation_py", "target": "validation_validate_dag", "relation": "contains", "confidence": "EXTRACTED", "source_file": "src/unified_algebra/validation.py", "source_location": "L83", "weight": 1.0}, {"source": "src_unified_algebra_validation_py", "target": "validation_validate_pipeline", "relation": "contains", "confidence": "EXTRACTED", "source_file": "src/unified_algebra/validation.py", "source_location": "L90", "weight": 1.0}, {"source": "src_unified_algebra_validation_py", "target": "validation_ua_primitives", "relation": "contains", "confidence": "EXTRACTED", "source_file": "src/unified_algebra/validation.py", "source_location": "L107", "weight": 1.0}, {"source": "validation_any_has_inputs", "target": "validation_eq_inputs", "relation": "calls", "confidence": "EXTRACTED", "source_file": "src/unified_algebra/validation.py", "source_location": "L36", "weight": 1.0}, {"source": "validation_resolve_dag", "target": "validation_eq_name", "relation": "calls", "confidence": "EXTRACTED", "source_file": "src/unified_algebra/validation.py", "source_location": "L48", "weight": 1.0}, {"source": "validation_resolve_dag", "target": "validation_eq_inputs", "relation": "calls", "confidence": "EXTRACTED", "source_file": "src/unified_algebra/validation.py", "source_location": "L56", "weight": 1.0}, {"source": "validation_validate_dag", "target": "validation_resolve_dag", "relation": "calls", "confidence": "EXTRACTED", "source_file": "src/unified_algebra/validation.py", "source_location": "L84", "weight": 1.0}, {"source": "validation_validate_pipeline", "target": "validation_any_has_inputs", "relation": "calls", "confidence": "EXTRACTED", "source_file": "src/unified_algebra/validation.py", "source_location": "L96", "weight": 1.0}, {"source": "validation_validate_pipeline", "target": "validation_validate_dag", "relation": "calls", "confidence": "EXTRACTED", "source_file": "src/unified_algebra/validation.py", "source_location": "L97", "weight": 1.0}, {"source": "validation_rationale_1", "target": "src_unified_algebra_validation_py", "relation": "rationale_for", "confidence": "EXTRACTED", "source_file": "src/unified_algebra/validation.py", "source_location": "L1", "weight": 1.0}, {"source": "validation_rationale_44", "target": "validation_resolve_dag", "relation": "rationale_for", "confidence": "EXTRACTED", "source_file": "src/unified_algebra/validation.py", "source_location": "L44", "weight": 1.0}, {"source": "validation_rationale_91", "target": "validation_validate_pipeline", "relation": "rationale_for", "confidence": "EXTRACTED", "source_file": "src/unified_algebra/validation.py", "source_location": "L91", "weight": 1.0}, {"source": "validation_rationale_111", "target": "validation_ua_primitives", "relation": "rationale_for", "confidence": "EXTRACTED", "source_file": "src/unified_algebra/validation.py", "source_location": "L111", "weight": 1.0}], "raw_calls": [{"caller_nid": "validation_eq_name", "callee": "string_value", "source_file": "src/unified_algebra/validation.py", "source_location": "L27"}, {"caller_nid": "validation_eq_name", "callee": "record_fields", "source_file": "src/unified_algebra/validation.py", "source_location": "L27"}, {"caller_nid": "validation_eq_inputs", "callee": "record_fields", "source_file": "src/unified_algebra/validation.py", "source_location": "L31"}, {"caller_nid": "validation_eq_inputs", "callee": "string_value", "source_file": "src/unified_algebra/validation.py", "source_location": "L32"}, {"caller_nid": "validation_any_has_inputs", "callee": "any", "source_file": "src/unified_algebra/validation.py", "source_location": "L36"}, {"caller_nid": "validation_resolve_dag", "callee": "enumerate", "source_file": "src/unified_algebra/validation.py", "source_location": "L56"}, {"caller_nid": "validation_resolve_dag", "callee": "append", "source_file": "src/unified_algebra/validation.py", "source_location": "L58"}, {"caller_nid": "validation_resolve_dag", "callee": "append", "source_file": "src/unified_algebra/validation.py", "source_location": "L59"}, {"caller_nid": "validation_resolve_dag", "callee": "deque", "source_file": "src/unified_algebra/validation.py", "source_location": "L63"}, {"caller_nid": "validation_resolve_dag", "callee": "items", "source_file": "src/unified_algebra/validation.py", "source_location": "L63"}, {"caller_nid": "validation_resolve_dag", "callee": "popleft", "source_file": "src/unified_algebra/validation.py", "source_location": "L66"}, {"caller_nid": "validation_resolve_dag", "callee": "append", "source_file": "src/unified_algebra/validation.py", "source_location": "L67"}, {"caller_nid": "validation_resolve_dag", "callee": "append", "source_file": "src/unified_algebra/validation.py", "source_location": "L71"}, {"caller_nid": "validation_resolve_dag", "callee": "len", "source_file": "src/unified_algebra/validation.py", "source_location": "L73"}, {"caller_nid": "validation_resolve_dag", "callee": "len", "source_file": "src/unified_algebra/validation.py", "source_location": "L73"}, {"caller_nid": "validation_resolve_dag", "callee": "ValueError", "source_file": "src/unified_algebra/validation.py", "source_location": "L74"}, {"caller_nid": "validation_validate_dag", "callee": "check_sort_junction", "source_file": "src/unified_algebra/validation.py", "source_location": "L86"}, {"caller_nid": "validation_validate_dag", "callee": "check_rank_junction", "source_file": "src/unified_algebra/validation.py", "source_location": "L87"}, {"caller_nid": "validation_validate_pipeline", "callee": "zip", "source_file": "src/unified_algebra/validation.py", "source_location": "L99"}, {"caller_nid": "validation_validate_pipeline", "callee": "check_sort_junction", "source_file": "src/unified_algebra/validation.py", "source_location": "L100"}, {"caller_nid": "validation_ua_primitives", "callee": "resolve_equation", "source_file": "src/unified_algebra/validation.py", "source_location": "L118"}]}