{
  "backend": "cupy",
  "operations": {
    "add":              {"kind": "elementwise binary", "path": "cupy.add",                "arity": 2, "arg_type": "FLOAT", "result_type": "FLOAT", "codec": "float64"},
    "subtract":         {"kind": "elementwise binary", "path": "cupy.subtract",           "arity": 2, "arg_type": "FLOAT", "result_type": "FLOAT", "codec": "float64"},
    "multiply":         {"kind": "elementwise binary", "path": "cupy.multiply",           "arity": 2, "arg_type": "FLOAT", "result_type": "FLOAT", "codec": "float64"},
    "divide":           {"kind": "elementwise binary", "path": "cupy.divide",             "arity": 2, "arg_type": "FLOAT", "result_type": "FLOAT", "codec": "float64"},
    "power":            {"kind": "elementwise binary", "path": "cupy.power",              "arity": 2, "arg_type": "FLOAT", "result_type": "FLOAT", "codec": "float64"},
    "minimum":          {"kind": "elementwise binary", "path": "cupy.minimum",            "arity": 2, "arg_type": "FLOAT", "result_type": "FLOAT", "codec": "float64"},
    "maximum":          {"kind": "elementwise binary", "path": "cupy.maximum",            "arity": 2, "arg_type": "FLOAT", "result_type": "FLOAT", "codec": "float64"},
    "logaddexp":        {"kind": "elementwise binary", "path": "cupy.logaddexp",          "arity": 2, "arg_type": "FLOAT", "result_type": "FLOAT", "codec": "float64"},

    "tanh":             {"kind": "unary", "path": "cupy.tanh",                            "arity": 1, "arg_type": "FLOAT", "result_type": "FLOAT", "codec": "float64"},
    "exp":              {"kind": "unary", "path": "cupy.exp",                             "arity": 1, "arg_type": "FLOAT", "result_type": "FLOAT", "codec": "float64"},
    "log":              {"kind": "unary", "path": "cupy.log",                             "arity": 1, "arg_type": "FLOAT", "result_type": "FLOAT", "codec": "float64"},
    "log1p":            {"kind": "unary", "path": "cupy.log1p",                           "arity": 1, "arg_type": "FLOAT", "result_type": "FLOAT", "codec": "float64"},
    "sqrt":             {"kind": "unary", "path": "cupy.sqrt",                            "arity": 1, "arg_type": "FLOAT", "result_type": "FLOAT", "codec": "float64"},
    "abs":              {"kind": "unary", "path": "cupy.abs",                             "arity": 1, "arg_type": "FLOAT", "result_type": "FLOAT", "codec": "float64"},
    "reciprocal":       {"kind": "unary", "path": "cupy.reciprocal",                      "arity": 1, "arg_type": "FLOAT", "result_type": "FLOAT", "codec": "float64"},
    "sign":             {"kind": "unary", "path": "cupy.sign",                            "arity": 1, "arg_type": "FLOAT", "result_type": "FLOAT", "codec": "float64"},
    "square":           {"kind": "unary", "path": "cupy.square",                          "arity": 1, "arg_type": "FLOAT", "result_type": "FLOAT", "codec": "float64"},
    "sin":              {"kind": "unary", "path": "cupy.sin",                             "arity": 1, "arg_type": "FLOAT", "result_type": "FLOAT", "codec": "float64"},
    "cos":              {"kind": "unary", "path": "cupy.cos",                             "arity": 1, "arg_type": "FLOAT", "result_type": "FLOAT", "codec": "float64"},
    "neg":              {"kind": "unary", "path": "cupy.negative",                        "arity": 1, "arg_type": "FLOAT", "result_type": "FLOAT", "codec": "float64"},

    "sigmoid":          {"kind": "unary", "path": "cupyx.scipy.special.expit",            "arity": 1, "arg_type": "FLOAT", "result_type": "FLOAT", "codec": "float64"},
    "softmax":          {"kind": "unary", "path": "cupyx.scipy.special.softmax",          "arity": 1, "arg_type": "FLOAT", "result_type": "FLOAT", "codec": "float64"},
    "reduce.logaddexp": {"kind": "reduce", "path": "cupyx.scipy.special.logsumexp",       "arity": 1, "arg_type": "FLOAT", "result_type": "FLOAT", "codec": "float64"},

    "reduce.add":       {"kind": "reduce", "path": "cupy.sum",                            "arity": 1, "arg_type": "FLOAT", "result_type": "FLOAT", "codec": "float64"},
    "reduce.multiply":  {"kind": "reduce", "path": "cupy.prod",                           "arity": 1, "arg_type": "FLOAT", "result_type": "FLOAT", "codec": "float64"},
    "reduce.minimum":   {"kind": "reduce", "path": "cupy.min",                            "arity": 1, "arg_type": "FLOAT", "result_type": "FLOAT", "codec": "float64"},
    "reduce.maximum":   {"kind": "reduce", "path": "cupy.max",                            "arity": 1, "arg_type": "FLOAT", "result_type": "FLOAT", "codec": "float64"}    
  }
}
