{"nodes": [{"id": "home_scanbot_unialg_src_unialg_morphism_functor_py", "label": "functor.py", "file_type": "code", "source_file": "/home/scanbot/unialg/src/unialg/morphism/functor.py", "source_location": "L1"}, {"id": "morphism_functor_polyexpr", "label": "PolyExpr", "file_type": "code", "source_file": "/home/scanbot/unialg/src/unialg/morphism/functor.py", "source_location": "L28"}, {"id": "morphism_functor_zero", "label": "Zero", "file_type": "code", "source_file": "/home/scanbot/unialg/src/unialg/morphism/functor.py", "source_location": "L33"}, {"id": "morphism_functor_one", "label": "One", "file_type": "code", "source_file": "/home/scanbot/unialg/src/unialg/morphism/functor.py", "source_location": "L38"}, {"id": "morphism_functor_id", "label": "Id", "file_type": "code", "source_file": "/home/scanbot/unialg/src/unialg/morphism/functor.py", "source_location": "L43"}, {"id": "morphism_functor_const", "label": "Const", "file_type": "code", "source_file": "/home/scanbot/unialg/src/unialg/morphism/functor.py", "source_location": "L48"}, {"id": "morphism_functor_sum", "label": "Sum", "file_type": "code", "source_file": "/home/scanbot/unialg/src/unialg/morphism/functor.py", "source_location": "L54"}, {"id": "morphism_functor_prod", "label": "Prod", "file_type": "code", "source_file": "/home/scanbot/unialg/src/unialg/morphism/functor.py", "source_location": "L61"}, {"id": "morphism_functor_exp", "label": "Exp", "file_type": "code", "source_file": "/home/scanbot/unialg/src/unialg/morphism/functor.py", "source_location": "L68"}, {"id": "morphism_functor_functor", "label": "Functor", "file_type": "code", "source_file": "/home/scanbot/unialg/src/unialg/morphism/functor.py", "source_location": "L118"}, {"id": "morphism_functor_functor_post_init", "label": ".__post_init__()", "file_type": "code", "source_file": "/home/scanbot/unialg/src/unialg/morphism/functor.py", "source_location": "L127"}, {"id": "morphism_functor_functor_summands", "label": ".summands()", "file_type": "code", "source_file": "/home/scanbot/unialg/src/unialg/morphism/functor.py", "source_location": "L134"}, {"id": "morphism_functor_functor_x_arity", "label": ".x_arity()", "file_type": "code", "source_file": "/home/scanbot/unialg/src/unialg/morphism/functor.py", "source_location": "L138"}, {"id": "morphism_functor_functor_is_recursive", "label": ".is_recursive()", "file_type": "code", "source_file": "/home/scanbot/unialg/src/unialg/morphism/functor.py", "source_location": "L142"}, {"id": "morphism_functor_functor_consts", "label": ".consts()", "file_type": "code", "source_file": "/home/scanbot/unialg/src/unialg/morphism/functor.py", "source_location": "L146"}, {"id": "morphism_functor_functor_repr", "label": ".__repr__()", "file_type": "code", "source_file": "/home/scanbot/unialg/src/unialg/morphism/functor.py", "source_location": "L150"}, {"id": "morphism_functor_pretty", "label": "pretty()", "file_type": "code", "source_file": "/home/scanbot/unialg/src/unialg/morphism/functor.py", "source_location": "L158"}, {"id": "morphism_functor_flatten_sum", "label": "_flatten_sum()", "file_type": "code", "source_file": "/home/scanbot/unialg/src/unialg/morphism/functor.py", "source_location": "L190"}, {"id": "morphism_functor_count_id", "label": "_count_id()", "file_type": "code", "source_file": "/home/scanbot/unialg/src/unialg/morphism/functor.py", "source_location": "L196"}, {"id": "morphism_functor_collect_consts", "label": "_collect_consts()", "file_type": "code", "source_file": "/home/scanbot/unialg/src/unialg/morphism/functor.py", "source_location": "L208"}, {"id": "morphism_functor_rationale_1", "label": "Polynomial endofunctor expressions.  A polynomial functor F : C \u2192 C is described", "file_type": "rationale", "source_file": "/home/scanbot/unialg/src/unialg/morphism/functor.py", "source_location": "L1"}, {"id": "morphism_functor_rationale_29", "label": "Base class for polynomial functor expressions.", "file_type": "rationale", "source_file": "/home/scanbot/unialg/src/unialg/morphism/functor.py", "source_location": "L29"}, {"id": "morphism_functor_rationale_34", "label": "F(X) = 0 \u2014 initial functor.", "file_type": "rationale", "source_file": "/home/scanbot/unialg/src/unialg/morphism/functor.py", "source_location": "L34"}, {"id": "morphism_functor_rationale_39", "label": "F(X) = 1 \u2014 constant terminal functor.", "file_type": "rationale", "source_file": "/home/scanbot/unialg/src/unialg/morphism/functor.py", "source_location": "L39"}, {"id": "morphism_functor_rationale_44", "label": "F(X) = X \u2014 the recursion variable. Not a concrete space.", "file_type": "rationale", "source_file": "/home/scanbot/unialg/src/unialg/morphism/functor.py", "source_location": "L44"}, {"id": "morphism_functor_rationale_49", "label": "F(X) = S \u2014 constant functor at space S.", "file_type": "rationale", "source_file": "/home/scanbot/unialg/src/unialg/morphism/functor.py", "source_location": "L49"}, {"id": "morphism_functor_rationale_55", "label": "F(X) = G(X) + H(X) \u2014 coproduct of functors.", "file_type": "rationale", "source_file": "/home/scanbot/unialg/src/unialg/morphism/functor.py", "source_location": "L55"}, {"id": "morphism_functor_rationale_62", "label": "F(X) = G(X) \u00d7 H(X) \u2014 product of functors.", "file_type": "rationale", "source_file": "/home/scanbot/unialg/src/unialg/morphism/functor.py", "source_location": "L62"}, {"id": "morphism_functor_rationale_69", "label": "F(X) = S \u2192 G(X) \u2014 exponential with constant base S.", "file_type": "rationale", "source_file": "/home/scanbot/unialg/src/unialg/morphism/functor.py", "source_location": "L69"}, {"id": "morphism_functor_rationale_109", "label": "F(X) = base \u2192 body(X).", "file_type": "rationale", "source_file": "/home/scanbot/unialg/src/unialg/morphism/functor.py", "source_location": "L109"}, {"id": "morphism_functor_rationale_119", "label": "Named polynomial endofunctor with a body expression and a category tag.      cat", "file_type": "rationale", "source_file": "/home/scanbot/unialg/src/unialg/morphism/functor.py", "source_location": "L119"}, {"id": "morphism_functor_rationale_135", "label": "Flatten the top-level Sum tree left-to-right into a tuple of summands.", "file_type": "rationale", "source_file": "/home/scanbot/unialg/src/unialg/morphism/functor.py", "source_location": "L135"}, {"id": "morphism_functor_rationale_139", "label": "Count of Id nodes (recursive positions) in the body.", "file_type": "rationale", "source_file": "/home/scanbot/unialg/src/unialg/morphism/functor.py", "source_location": "L139"}, {"id": "morphism_functor_rationale_143", "label": "True if the functor has at least one recursive position.", "file_type": "rationale", "source_file": "/home/scanbot/unialg/src/unialg/morphism/functor.py", "source_location": "L143"}, {"id": "morphism_functor_rationale_147", "label": "All SpaceT values from Const.space and Exp.base nodes, depth-first.", "file_type": "rationale", "source_file": "/home/scanbot/unialg/src/unialg/morphism/functor.py", "source_location": "L147"}, {"id": "morphism_functor_rationale_159", "label": "Human-readable string for a PolyExpr.", "file_type": "rationale", "source_file": "/home/scanbot/unialg/src/unialg/morphism/functor.py", "source_location": "L159"}], "edges": [{"source": "home_scanbot_unialg_src_unialg_morphism_functor_py", "target": "dataclasses", "relation": "imports_from", "context": "import", "confidence": "EXTRACTED", "source_file": "/home/scanbot/unialg/src/unialg/morphism/functor.py", "source_location": "L22", "weight": 1.0}, {"source": "home_scanbot_unialg_src_unialg_morphism_functor_py", "target": "unialg_space", "relation": "imports_from", "context": "import", "confidence": "EXTRACTED", "source_file": "/home/scanbot/unialg/src/unialg/morphism/functor.py", "source_location": "L24", "weight": 1.0}, {"source": "home_scanbot_unialg_src_unialg_morphism_functor_py", "target": "morphism_functor_polyexpr", "relation": "contains", "confidence": "EXTRACTED", "source_file": "/home/scanbot/unialg/src/unialg/morphism/functor.py", "source_location": "L28", "weight": 1.0}, {"source": "home_scanbot_unialg_src_unialg_morphism_functor_py", "target": "morphism_functor_zero", "relation": "contains", "confidence": "EXTRACTED", "source_file": "/home/scanbot/unialg/src/unialg/morphism/functor.py", "source_location": "L33", "weight": 1.0}, {"source": "morphism_functor_zero", "target": "morphism_functor_polyexpr", "relation": "inherits", "confidence": "EXTRACTED", "source_file": "/home/scanbot/unialg/src/unialg/morphism/functor.py", "source_location": "L33", "weight": 1.0}, {"source": "home_scanbot_unialg_src_unialg_morphism_functor_py", "target": "morphism_functor_one", "relation": "contains", "confidence": "EXTRACTED", "source_file": "/home/scanbot/unialg/src/unialg/morphism/functor.py", "source_location": "L38", "weight": 1.0}, {"source": "morphism_functor_one", "target": "morphism_functor_polyexpr", "relation": "inherits", "confidence": "EXTRACTED", "source_file": "/home/scanbot/unialg/src/unialg/morphism/functor.py", "source_location": "L38", "weight": 1.0}, {"source": "home_scanbot_unialg_src_unialg_morphism_functor_py", "target": "morphism_functor_id", "relation": "contains", "confidence": "EXTRACTED", "source_file": "/home/scanbot/unialg/src/unialg/morphism/functor.py", "source_location": "L43", "weight": 1.0}, {"source": "morphism_functor_id", "target": "morphism_functor_polyexpr", "relation": "inherits", "confidence": "EXTRACTED", "source_file": "/home/scanbot/unialg/src/unialg/morphism/functor.py", "source_location": "L43", "weight": 1.0}, {"source": "home_scanbot_unialg_src_unialg_morphism_functor_py", "target": "morphism_functor_const", "relation": "contains", "confidence": "EXTRACTED", "source_file": "/home/scanbot/unialg/src/unialg/morphism/functor.py", "source_location": "L48", "weight": 1.0}, {"source": "morphism_functor_const", "target": "morphism_functor_polyexpr", "relation": "inherits", "confidence": "EXTRACTED", "source_file": "/home/scanbot/unialg/src/unialg/morphism/functor.py", "source_location": "L48", "weight": 1.0}, {"source": "home_scanbot_unialg_src_unialg_morphism_functor_py", "target": "morphism_functor_sum", "relation": "contains", "confidence": "EXTRACTED", "source_file": "/home/scanbot/unialg/src/unialg/morphism/functor.py", "source_location": "L54", "weight": 1.0}, {"source": "morphism_functor_sum", "target": "morphism_functor_polyexpr", "relation": "inherits", "confidence": "EXTRACTED", "source_file": "/home/scanbot/unialg/src/unialg/morphism/functor.py", "source_location": "L54", "weight": 1.0}, {"source": "home_scanbot_unialg_src_unialg_morphism_functor_py", "target": "morphism_functor_prod", "relation": "contains", "confidence": "EXTRACTED", "source_file": "/home/scanbot/unialg/src/unialg/morphism/functor.py", "source_location": "L61", "weight": 1.0}, {"source": "morphism_functor_prod", "target": "morphism_functor_polyexpr", "relation": "inherits", "confidence": "EXTRACTED", "source_file": "/home/scanbot/unialg/src/unialg/morphism/functor.py", "source_location": "L61", "weight": 1.0}, {"source": "home_scanbot_unialg_src_unialg_morphism_functor_py", "target": "morphism_functor_exp", "relation": "contains", "confidence": "EXTRACTED", "source_file": "/home/scanbot/unialg/src/unialg/morphism/functor.py", "source_location": "L68", "weight": 1.0}, {"source": "morphism_functor_exp", "target": "morphism_functor_polyexpr", "relation": "inherits", "confidence": "EXTRACTED", "source_file": "/home/scanbot/unialg/src/unialg/morphism/functor.py", "source_location": "L68", "weight": 1.0}, {"source": "home_scanbot_unialg_src_unialg_morphism_functor_py", "target": "morphism_functor_zero", "relation": "contains", "confidence": "EXTRACTED", "source_file": "/home/scanbot/unialg/src/unialg/morphism/functor.py", "source_location": "L78", "weight": 1.0}, {"source": "home_scanbot_unialg_src_unialg_morphism_functor_py", "target": "morphism_functor_one", "relation": "contains", "confidence": "EXTRACTED", "source_file": "/home/scanbot/unialg/src/unialg/morphism/functor.py", "source_location": "L83", "weight": 1.0}, {"source": "home_scanbot_unialg_src_unialg_morphism_functor_py", "target": "morphism_functor_id", "relation": "contains", "confidence": "EXTRACTED", "source_file": "/home/scanbot/unialg/src/unialg/morphism/functor.py", "source_location": "L88", "weight": 1.0}, {"source": "home_scanbot_unialg_src_unialg_morphism_functor_py", "target": "morphism_functor_const", "relation": "contains", "confidence": "EXTRACTED", "source_file": "/home/scanbot/unialg/src/unialg/morphism/functor.py", "source_location": "L93", "weight": 1.0}, {"source": "home_scanbot_unialg_src_unialg_morphism_functor_py", "target": "morphism_functor_sum", "relation": "contains", "confidence": "EXTRACTED", "source_file": "/home/scanbot/unialg/src/unialg/morphism/functor.py", "source_location": "L98", "weight": 1.0}, {"source": "home_scanbot_unialg_src_unialg_morphism_functor_py", "target": "morphism_functor_prod", "relation": "contains", "confidence": "EXTRACTED", "source_file": "/home/scanbot/unialg/src/unialg/morphism/functor.py", "source_location": "L103", "weight": 1.0}, {"source": "home_scanbot_unialg_src_unialg_morphism_functor_py", "target": "morphism_functor_exp", "relation": "contains", "confidence": "EXTRACTED", "source_file": "/home/scanbot/unialg/src/unialg/morphism/functor.py", "source_location": "L108", "weight": 1.0}, {"source": "home_scanbot_unialg_src_unialg_morphism_functor_py", "target": "morphism_functor_functor", "relation": "contains", "confidence": "EXTRACTED", "source_file": "/home/scanbot/unialg/src/unialg/morphism/functor.py", "source_location": "L118", "weight": 1.0}, {"source": "morphism_functor_functor", "target": "morphism_functor_functor_post_init", "relation": "method", "confidence": "EXTRACTED", "source_file": "/home/scanbot/unialg/src/unialg/morphism/functor.py", "source_location": "L127", "weight": 1.0}, {"source": "morphism_functor_functor", "target": "morphism_functor_functor_summands", "relation": "method", "confidence": "EXTRACTED", "source_file": "/home/scanbot/unialg/src/unialg/morphism/functor.py", "source_location": "L134", "weight": 1.0}, {"source": "morphism_functor_functor", "target": "morphism_functor_functor_x_arity", "relation": "method", "confidence": "EXTRACTED", "source_file": "/home/scanbot/unialg/src/unialg/morphism/functor.py", "source_location": "L138", "weight": 1.0}, {"source": "morphism_functor_functor", "target": "morphism_functor_functor_is_recursive", "relation": "method", "confidence": "EXTRACTED", "source_file": "/home/scanbot/unialg/src/unialg/morphism/functor.py", "source_location": "L142", "weight": 1.0}, {"source": "morphism_functor_functor", "target": "morphism_functor_functor_consts", "relation": "method", "confidence": "EXTRACTED", "source_file": "/home/scanbot/unialg/src/unialg/morphism/functor.py", "source_location": "L146", "weight": 1.0}, {"source": "morphism_functor_functor", "target": "morphism_functor_functor_repr", "relation": "method", "confidence": "EXTRACTED", "source_file": "/home/scanbot/unialg/src/unialg/morphism/functor.py", "source_location": "L150", "weight": 1.0}, {"source": "home_scanbot_unialg_src_unialg_morphism_functor_py", "target": "morphism_functor_pretty", "relation": "contains", "confidence": "EXTRACTED", "source_file": "/home/scanbot/unialg/src/unialg/morphism/functor.py", "source_location": "L158", "weight": 1.0}, {"source": "home_scanbot_unialg_src_unialg_morphism_functor_py", "target": "morphism_functor_flatten_sum", "relation": "contains", "confidence": "EXTRACTED", "source_file": "/home/scanbot/unialg/src/unialg/morphism/functor.py", "source_location": "L190", "weight": 1.0}, {"source": "home_scanbot_unialg_src_unialg_morphism_functor_py", "target": "morphism_functor_count_id", "relation": "contains", "confidence": "EXTRACTED", "source_file": "/home/scanbot/unialg/src/unialg/morphism/functor.py", "source_location": "L196", "weight": 1.0}, {"source": "home_scanbot_unialg_src_unialg_morphism_functor_py", "target": "morphism_functor_collect_consts", "relation": "contains", "confidence": "EXTRACTED", "source_file": "/home/scanbot/unialg/src/unialg/morphism/functor.py", "source_location": "L208", "weight": 1.0}, {"source": "morphism_functor_functor_summands", "target": "morphism_functor_flatten_sum", "relation": "calls", "context": "call", "confidence": "EXTRACTED", "source_file": "/home/scanbot/unialg/src/unialg/morphism/functor.py", "source_location": "L136", "weight": 1.0}, {"source": "morphism_functor_functor_x_arity", "target": "morphism_functor_count_id", "relation": "calls", "context": "call", "confidence": "EXTRACTED", "source_file": "/home/scanbot/unialg/src/unialg/morphism/functor.py", "source_location": "L140", "weight": 1.0}, {"source": "morphism_functor_functor_is_recursive", "target": "morphism_functor_functor_x_arity", "relation": "calls", "context": "call", "confidence": "EXTRACTED", "source_file": "/home/scanbot/unialg/src/unialg/morphism/functor.py", "source_location": "L144", "weight": 1.0}, {"source": "morphism_functor_functor_consts", "target": "morphism_functor_collect_consts", "relation": "calls", "context": "call", "confidence": "EXTRACTED", "source_file": "/home/scanbot/unialg/src/unialg/morphism/functor.py", "source_location": "L148", "weight": 1.0}, {"source": "morphism_functor_functor_repr", "target": "morphism_functor_pretty", "relation": "calls", "context": "call", "confidence": "EXTRACTED", "source_file": "/home/scanbot/unialg/src/unialg/morphism/functor.py", "source_location": "L151", "weight": 1.0}, {"source": "morphism_functor_rationale_1", "target": "home_scanbot_unialg_src_unialg_morphism_functor_py", "relation": "rationale_for", "confidence": "EXTRACTED", "source_file": "/home/scanbot/unialg/src/unialg/morphism/functor.py", "source_location": "L1", "weight": 1.0}, {"source": "morphism_functor_rationale_29", "target": "morphism_functor_polyexpr", "relation": "rationale_for", "confidence": "EXTRACTED", "source_file": "/home/scanbot/unialg/src/unialg/morphism/functor.py", "source_location": "L29", "weight": 1.0}, {"source": "morphism_functor_rationale_34", "target": "morphism_functor_zero", "relation": "rationale_for", "confidence": "EXTRACTED", "source_file": "/home/scanbot/unialg/src/unialg/morphism/functor.py", "source_location": "L34", "weight": 1.0}, {"source": "morphism_functor_rationale_39", "target": "morphism_functor_one", "relation": "rationale_for", "confidence": "EXTRACTED", "source_file": "/home/scanbot/unialg/src/unialg/morphism/functor.py", "source_location": "L39", "weight": 1.0}, {"source": "morphism_functor_rationale_44", "target": "morphism_functor_id", "relation": "rationale_for", "confidence": "EXTRACTED", "source_file": "/home/scanbot/unialg/src/unialg/morphism/functor.py", "source_location": "L44", "weight": 1.0}, {"source": "morphism_functor_rationale_49", "target": "morphism_functor_const", "relation": "rationale_for", "confidence": "EXTRACTED", "source_file": "/home/scanbot/unialg/src/unialg/morphism/functor.py", "source_location": "L49", "weight": 1.0}, {"source": "morphism_functor_rationale_55", "target": "morphism_functor_sum", "relation": "rationale_for", "confidence": "EXTRACTED", "source_file": "/home/scanbot/unialg/src/unialg/morphism/functor.py", "source_location": "L55", "weight": 1.0}, {"source": "morphism_functor_rationale_62", "target": "morphism_functor_prod", "relation": "rationale_for", "confidence": "EXTRACTED", "source_file": "/home/scanbot/unialg/src/unialg/morphism/functor.py", "source_location": "L62", "weight": 1.0}, {"source": "morphism_functor_rationale_69", "target": "morphism_functor_exp", "relation": "rationale_for", "confidence": "EXTRACTED", "source_file": "/home/scanbot/unialg/src/unialg/morphism/functor.py", "source_location": "L69", "weight": 1.0}, {"source": "morphism_functor_rationale_109", "target": "morphism_functor_exp", "relation": "rationale_for", "confidence": "EXTRACTED", "source_file": "/home/scanbot/unialg/src/unialg/morphism/functor.py", "source_location": "L109", "weight": 1.0}, {"source": "morphism_functor_rationale_119", "target": "morphism_functor_functor", "relation": "rationale_for", "confidence": "EXTRACTED", "source_file": "/home/scanbot/unialg/src/unialg/morphism/functor.py", "source_location": "L119", "weight": 1.0}, {"source": "morphism_functor_rationale_135", "target": "morphism_functor_functor_summands", "relation": "rationale_for", "confidence": "EXTRACTED", "source_file": "/home/scanbot/unialg/src/unialg/morphism/functor.py", "source_location": "L135", "weight": 1.0}, {"source": "morphism_functor_rationale_139", "target": "morphism_functor_functor_x_arity", "relation": "rationale_for", "confidence": "EXTRACTED", "source_file": "/home/scanbot/unialg/src/unialg/morphism/functor.py", "source_location": "L139", "weight": 1.0}, {"source": "morphism_functor_rationale_143", "target": "morphism_functor_functor_is_recursive", "relation": "rationale_for", "confidence": "EXTRACTED", "source_file": "/home/scanbot/unialg/src/unialg/morphism/functor.py", "source_location": "L143", "weight": 1.0}, {"source": "morphism_functor_rationale_147", "target": "morphism_functor_functor_consts", "relation": "rationale_for", "confidence": "EXTRACTED", "source_file": "/home/scanbot/unialg/src/unialg/morphism/functor.py", "source_location": "L147", "weight": 1.0}, {"source": "morphism_functor_rationale_159", "target": "morphism_functor_pretty", "relation": "rationale_for", "confidence": "EXTRACTED", "source_file": "/home/scanbot/unialg/src/unialg/morphism/functor.py", "source_location": "L159", "weight": 1.0}], "raw_calls": [{"caller_nid": "morphism_functor_functor_post_init", "callee": "isinstance", "is_member_call": false, "source_file": "/home/scanbot/unialg/src/unialg/morphism/functor.py", "source_location": "L128"}, {"caller_nid": "morphism_functor_functor_post_init", "callee": "ValueError", "is_member_call": false, "source_file": "/home/scanbot/unialg/src/unialg/morphism/functor.py", "source_location": "L129"}, {"caller_nid": "morphism_functor_functor_post_init", "callee": "type", "is_member_call": false, "source_file": "/home/scanbot/unialg/src/unialg/morphism/functor.py", "source_location": "L131"}, {"caller_nid": "morphism_functor_pretty", "callee": "isinstance", "is_member_call": false, "source_file": "/home/scanbot/unialg/src/unialg/morphism/functor.py", "source_location": "L160"}, {"caller_nid": "morphism_functor_pretty", "callee": "isinstance", "is_member_call": false, "source_file": "/home/scanbot/unialg/src/unialg/morphism/functor.py", "source_location": "L162"}, {"caller_nid": "morphism_functor_pretty", "callee": "isinstance", "is_member_call": false, "source_file": "/home/scanbot/unialg/src/unialg/morphism/functor.py", "source_location": "L164"}, {"caller_nid": "morphism_functor_pretty", "callee": "isinstance", "is_member_call": false, "source_file": "/home/scanbot/unialg/src/unialg/morphism/functor.py", "source_location": "L166"}, {"caller_nid": "morphism_functor_pretty", "callee": "isinstance", "is_member_call": false, "source_file": "/home/scanbot/unialg/src/unialg/morphism/functor.py", "source_location": "L168"}, {"caller_nid": "morphism_functor_pretty", "callee": "isinstance", "is_member_call": false, "source_file": "/home/scanbot/unialg/src/unialg/morphism/functor.py", "source_location": "L170"}, {"caller_nid": "morphism_functor_pretty", "callee": "isinstance", "is_member_call": false, "source_file": "/home/scanbot/unialg/src/unialg/morphism/functor.py", "source_location": "L173"}, {"caller_nid": "morphism_functor_pretty", "callee": "isinstance", "is_member_call": false, "source_file": "/home/scanbot/unialg/src/unialg/morphism/functor.py", "source_location": "L175"}, {"caller_nid": "morphism_functor_pretty", "callee": "isinstance", "is_member_call": false, "source_file": "/home/scanbot/unialg/src/unialg/morphism/functor.py", "source_location": "L178"}, {"caller_nid": "morphism_functor_pretty", "callee": "isinstance", "is_member_call": false, "source_file": "/home/scanbot/unialg/src/unialg/morphism/functor.py", "source_location": "L180"}, {"caller_nid": "morphism_functor_pretty", "callee": "ValueError", "is_member_call": false, "source_file": "/home/scanbot/unialg/src/unialg/morphism/functor.py", "source_location": "L183"}, {"caller_nid": "morphism_functor_pretty", "callee": "type", "is_member_call": false, "source_file": "/home/scanbot/unialg/src/unialg/morphism/functor.py", "source_location": "L183"}, {"caller_nid": "morphism_functor_flatten_sum", "callee": "isinstance", "is_member_call": false, "source_file": "/home/scanbot/unialg/src/unialg/morphism/functor.py", "source_location": "L191"}, {"caller_nid": "morphism_functor_count_id", "callee": "isinstance", "is_member_call": false, "source_file": "/home/scanbot/unialg/src/unialg/morphism/functor.py", "source_location": "L197"}, {"caller_nid": "morphism_functor_count_id", "callee": "isinstance", "is_member_call": false, "source_file": "/home/scanbot/unialg/src/unialg/morphism/functor.py", "source_location": "L199"}, {"caller_nid": "morphism_functor_count_id", "callee": "isinstance", "is_member_call": false, "source_file": "/home/scanbot/unialg/src/unialg/morphism/functor.py", "source_location": "L201"}, {"caller_nid": "morphism_functor_count_id", "callee": "isinstance", "is_member_call": false, "source_file": "/home/scanbot/unialg/src/unialg/morphism/functor.py", "source_location": "L203"}, {"caller_nid": "morphism_functor_count_id", "callee": "ValueError", "is_member_call": false, "source_file": "/home/scanbot/unialg/src/unialg/morphism/functor.py", "source_location": "L205"}, {"caller_nid": "morphism_functor_count_id", "callee": "type", "is_member_call": false, "source_file": "/home/scanbot/unialg/src/unialg/morphism/functor.py", "source_location": "L205"}, {"caller_nid": "morphism_functor_collect_consts", "callee": "isinstance", "is_member_call": false, "source_file": "/home/scanbot/unialg/src/unialg/morphism/functor.py", "source_location": "L209"}, {"caller_nid": "morphism_functor_collect_consts", "callee": "isinstance", "is_member_call": false, "source_file": "/home/scanbot/unialg/src/unialg/morphism/functor.py", "source_location": "L211"}, {"caller_nid": "morphism_functor_collect_consts", "callee": "isinstance", "is_member_call": false, "source_file": "/home/scanbot/unialg/src/unialg/morphism/functor.py", "source_location": "L213"}, {"caller_nid": "morphism_functor_collect_consts", "callee": "isinstance", "is_member_call": false, "source_file": "/home/scanbot/unialg/src/unialg/morphism/functor.py", "source_location": "L215"}, {"caller_nid": "morphism_functor_collect_consts", "callee": "ValueError", "is_member_call": false, "source_file": "/home/scanbot/unialg/src/unialg/morphism/functor.py", "source_location": "L217"}, {"caller_nid": "morphism_functor_collect_consts", "callee": "type", "is_member_call": false, "source_file": "/home/scanbot/unialg/src/unialg/morphism/functor.py", "source_location": "L217"}]}